scripts/__init__.py
scripts/main.py
easy_alias-0.0.1.dist-info/METADATA
easy_alias-0.0.1.dist-info/WHEEL
easy_alias-0.0.1.dist-info/entry_points.txt
easy_alias-0.0.1.dist-info/top_level.txt
easy_alias-0.0.1.dist-info/RECORD
