Metadata-Version: 2.1
Name: easy-alias
Version: 0.0.1
Summary: A simple and easy command alias tool
Home-page: https://github.com/fadeawaylove/easy_alias
Author: daigua
Author-email: 1032939141@qq.com
Requires-Python: >=3.6
Requires-Dist: Click
